Workbook

Sheet 00 Escolha_Principal
A1: Planejamento de Dropshipping no Brasil
A2: Decisão executiva para iniciar com menor risco: foco em utilidade clara, margem realista, fornecedores validados e testes pequenos.
A4: Nicho recomendado | D4: Capital inicial | G4: Fornecedor inicial | J4: Canal orgânico | M4: Canal pago
A5: Casa, organização e utilidades práticas | D5: R$ 400 a R$ 1.000 | G5: Dropi ou nacional direto | J5: TikTok + Reels | M5: Meta Ads + TikTok Ads
A9: Resumo executivo | B9: Decisão recomendada
A10: Produto inicial mais seguro | B10: Organizador de cabos ou suporte adesivo para tomada
A11: Principais riscos | B11: Prazo longo, fornecedor ruim, margem apertada, reembolso e criativo fraco
A12: Estratégia inicial | B12: Começar com 3 a 5 produtos simples, comprar amostra, criar página limpa, validar criativos orgânicos e só então testar anúncios com orçamento controlado.
A13: Caminho de menor risco | B13: Priorizar fornecedor nacional ou plataforma com rastreio, política clara, checkout simples, atendimento em até 24h e reserva para reembolso.
A14: Regra de decisão | B14: Escalar apenas quando houver margem líquida positiva, entrega previsível, criativo validado e reclamações sob controle.
A17: Nicho | B17: Nota | C17: Recomendado | E17: Cenário | F17: Investimento estimado | H17: Cenário | I17: Lucro estimado no mês 3 | K17: Evitar no começo | L17: Motivo
A18: Casa, organização e utilidades práticas | B18: 9.7 | C18: Sim | E18: Econômico | F18: ='06 Custos_Iniciais'!C17 | H18: Ruim | I18: ='15 Financeiro_3_Meses'!N7 | K18: Suplementos e produtos médicos | L18: Risco regulatório, promessa sensível e bloqueios de anúncio
A19: Pet utilitário | B19: 8.8 | C19: Sim | E19: Intermediário | F19: ='06 Custos_Iniciais'!D17 | H19: Médio | I19: ='15 Financeiro_3_Meses'!N10 | K19: Cosméticos com promessa forte | L19: Risco Anvisa, reembolso e publicidade enganosa
A20: Cozinha prática | B20: 8.5 | C20: Sim | E20: Profissional | F20: ='06 Custos_Iniciais'!E17 | H20: Bom | I20: ='15 Financeiro_3_Meses'!N13 | K20: Eletrônicos complexos ou com bateria ruim | L20: Defeito, devolução e suporte difícil
A21: Automotivo leve | B21: 8.3 | C21: Sim | K21: Moda com numeração | L21: Trocas frequentes e variação de tamanho
A22: Fitness leve e bem-estar sem promessa médica | B22: 7.6 | C22: Parcial | K22: Produtos falsificados, réplicas e marcas sem autorização | L22: Risco legal e bloqueio de conta
A23: Beleza não regulada | B23: 7.4 | C23: Parcial | K23: Produtos infantis com risco de segurança | L23: Alto risco operacional e reputacional
A42: Observação: a planilha usa estimativas realistas e não promete lucro. Dados de plataformas, preços, integrações, regras e tributos devem ser validados em fontes oficiais.

Sheet 01 Visao_Geral
A1: Tema | B1: Resumo prático
A2: Como funciona | B2: O cliente compra na loja, você compra do fornecedor e o fornecedor envia diretamente ao cliente.
A3: Etapas da venda | B3: Pesquisa, validação, loja, tráfego, pedido, compra no fornecedor, envio, rastreamento, atendimento e pós-venda.
A4: Como o lucro é formado | B4: Lucro é preço de venda menos produto, frete, taxas, anúncios, impostos, reembolsos, ferramentas e suporte.
A5: Principal cuidado | B5: Não anunciar produto sem validar amostra, prazo, margem e política de troca.
A6: O que não fazer | B6: Não vender produto proibido, falsificado, perigoso, com promessa médica ou sem margem realista.
A7: Expectativa realista | B7: Pode gerar lucro, mas exige teste, atendimento, controle financeiro e tolerância a erro controlado.
A8: Risco inicial | B8: Atraso, fornecedor ruim, reembolso, chargeback e conta de anúncios bloqueada podem inviabilizar a operação.
A9: Métrica de saúde | B9: Margem líquida positiva, reclamações baixas, entrega previsível e criativo com CPA aceitável.
A10: Caminho seguro | B10: Começar pequeno, documentar tudo, medir cada etapa e reinvestir apenas parte do lucro.

Sheet 02 Modelo_Negocio
A1: Etapa | B1: O que fazer | C1: Ferramenta sugerida | D1: Erro comum | E1: Como evitar
A2: Pesquisa de nicho | B2: Mapear dores, intenção de compra e concorrência. | C2: Google Trends, TikTok, Instagram, Mercado Livre | D2: Escolher nicho só por gosto pessoal. | E2: Comparar demanda, margem e risco.
A3: Escolha do produto | B3: Priorizar utilidade clara, ticket acessível e baixo risco de defeito. | C3: Dropi, DSers, DropNacional, marketplaces | D3: Comprar produto apenas porque viralizou. | E3: Avaliar qualidade, prazo, avaliações e margem.
A4: Validação | B4: Confirmar amostra, criativo, fornecedor, prazo e preço. | C4: Planilha, pedido teste, vídeos orgânicos | D4: Anunciar sem testar. | E4: Comprar amostra e medir resposta orgânica.
A5: Fornecedor | B5: Verificar reputação, estoque, rastreio e política de troca. | C5: Dropi, DropNacional, fornecedor direto | D5: Depender de fornecedor sem contato. | E5: Ter fornecedor alternativo e SLA mínimo.
A6: Criação da loja | B6: Montar páginas claras, políticas, checkout simples e prova social honesta. | C6: Nuvemshop, Shopify, Yampi, WooCommerce | D6: Loja com aparência improvisada. | E6: Usar layout limpo, imagens reais e texto objetivo.
A7: Anúncio | B7: Testar criativos com orçamento pequeno e metas claras. | C7: Meta Ads, TikTok Ads | D7: Escalar sem dados. | E7: Definir CPA máximo e regra de pausa.
A8: Venda | B8: Receber pedido com prazo e comunicação transparentes. | C8: Loja, gateway, WhatsApp Business | D8: Prometer prazo irreal. | E8: Informar prazo conservador e rastreio.
A9: Compra no fornecedor | B9: Comprar corretamente após a venda e registrar evidências. | C9: Fornecedor, planilha, automação | D9: Comprar item errado ou sem rastreio. | E9: Padronizar SKU e checklist de pedido.
A10: Envio | B10: Acompanhar despacho, rastreio e exceções. | C10: Melhor Envio, rastreio do fornecedor | D10: Não monitorar pedido. | E10: Rotina diária de rastreio.
A11: Rastreamento | B11: Avisar cliente sobre status e atraso antes da reclamação. | C11: E-mail, WhatsApp, página de rastreio | D11: Cliente sem informação. | E11: Enviar atualizações claras.
A12: Atendimento | B12: Responder rápido, com registro e linguagem profissional. | C12: WhatsApp Business, e-mail, helpdesk | D12: Responder tarde ou de forma genérica. | E12: Criar respostas rápidas e SLA de 24h.
... A14: Reinvestimento | B14: Separar reserva, impostos, reembolso e verba de teste. | C14: Planilha financeira | D14: Gastar todo o lucro aparente. | E14: Definir percentual de reinvestimento e reserva.

Sheet 03 Nichos
A1: Ranking | B1: Nicho | C1: Nota de 0 a 10 | D1: Potencial de venda | E1: Concorrência | F1: Ticket médio estimado | G1: Facilidade de anunciar | H1: Risco operacional | I1: Produtos indicados | J1: Perfil do cliente | K1: Recomendado para iniciante | L1: Justificativa
A2: 1 | B2: Casa, organização e utilidades práticas | C2: 9.7 | D2: Alto | E2: Média | F2: R$ 40 a R$ 120 | G2: Alta | H2: Baixo | I2: Organizador de cabos, suporte adesivo, organizador de geladeira | J2: Pessoas que querem praticidade em casa, escritório ou pequenos espaços | K2: Sim | L2: Produtos simples, visuais, fáceis de demonstrar e com baixo risco técnico.
A3: 2 | B3: Pet utilitário | C3: 8.8 | D3: Alto | E3: Média | F3: R$ 35 a R$ 100 | G3: Alta | H3: Baixo | I3: Escova removedora de pelos, tapete higiênico, bebedouro portátil | J3: Tutores de pets que buscam higiene, passeio e organização | K3: Sim | L3: Boa resposta em vídeos curtos; evitar ração, remédios e promessas veterinárias.
A4: 3 | B4: Cozinha prática | C4: 8.5 | D4: Médio/alto | E4: Média | F4: R$ 30 a R$ 90 | G4: Alta | H4: Médio | I4: Cortador prático, porta-temperos, escorredor dobrável | J4: Famílias, pessoas que cozinham e pequenos apartamentos | K4: Sim | L4: Problemas cotidianos são claros; evitar itens frágeis ou elétricos complexos.
A5: 4 | B5: Automotivo leve | C5: 8.3 | D5: Médio/alto | E5: Média | F5: R$ 35 a R$ 110 | G5: Média/alta | H5: Médio | I5: Suporte veicular, lixeira dobrável, organizador de banco | J5: Motoristas, motoristas de aplicativo e famílias | K5: Sim | L5: Funciona bem com antes/depois; evitar peças mecânicas e instalação técnica.
A6: 5 | B6: Fitness leve e bem-estar sem promessa médica | C6: 7.6 | D6: Médio | E6: Alta | F6: R$ 30 a R$ 90 | G6: Média | H6: Médio | I6: Garrafas, bolsas, elásticos e organizadores de treino | J6: Pessoas que treinam em casa ou buscam rotina mais organizada | K6: Parcial | L6: Pode vender, mas exige cuidado para não prometer saúde, cura ou emagrecimento.
A7: 6 | B7: Beleza não regulada | C7: 7.4 | D7: Médio | E7: Alta | F7: R$ 25 a R$ 90 | G7: Média | H7: Médio | I7: Organizador de maquiagem, nécessaire, espelho compacto | J7: Pessoas interessadas em organização, rotina e estética sem cosméticos | K7: Parcial | L7: Evitar cosméticos, dermocosméticos, clareadores e promessas reguladas pela Anvisa.

Sheet 04 Produtos
A1: Nicho | B1: Produto | C1: Problema que resolve | D1: Público-alvo | E1: Custo estimado | F1: Frete estimado | G1: Preço de venda sugerido | H1: Taxas estimadas | I1: CPA máximo aceitável | J1: Margem estimada | K1: Risco | L1: Fornecedor sugerido | M1: Tipo de criativo ideal | N1: Observações
A2: Casa, organização e utilidades práticas | B2: Organizador de cabos | C2: Reduz bagunça e risco de fios soltos. | D2: Residências, home office e escritórios | E2: 14.9 | F2: 8.9 | G2: 49.9 | H2: 8 | I2: 7.5 | J2: =IF(G2=0,0,(G2-E2-F2-H2-I2)/G2) | K2: Baixo | L2: Dropi | M2: Vídeo de instalação em menos de 10 segundos | N2: Produto simples, visual e fácil de explicar.
A3: Casa, organização e utilidades práticas | B3: Suporte adesivo para tomada | C3: Organiza tomadas, carregadores e pequenos aparelhos. | D3: Famílias e pessoas com pouco espaço | E3: 11.5 | F3: 8.5 | G3: 39.9 | H3: 7 | I3: 6.5 | J3: =IF(G3=0,0,(G3-E3-F3-H3-I3)/G3) | K3: Baixo | L3: AliExpress + DSers | M3: Antes e depois na cozinha ou escritório | N3: Validar cola e acabamento com amostra.
A4: Pet utilitário | B4: Escova removedora de pelos pet | C4: Remove pelos de sofá, roupa e tapete. | D4: Tutores de cães e gatos | E4: 18.5 | F4: 9.5 | G4: 59.9 | H4: 8.5 | I4: 8 | J4: =IF(G4=0,0,(G4-E4-F4-H4-I4)/G4) | K4: Baixo | L4: Dropi | M4: Demonstração real em tecido escuro | N4: Apelo visual forte; não fazer promessa veterinária.
A5: Pet utilitário | B5: Luva removedora de pelos | C5: Ajuda a tirar pelos soltos durante carinho e escovação. | D5: Tutores de pets que soltam pelo | E5: 13.9 | F5: 8.9 | G5: 49.9 | H5: 7.5 | I5: 7 | J5: =IF(G5=0,0,(G5-E5-F5-H5-I5)/G5) | K5: Baixo | L5: AliExpress + DSers | M5: Uso real com pet calmo | N5: Evitar linguagem de tratamento veterinário.
A6: Casa, organização e utilidades práticas | B6: Organizador de geladeira | C6: Melhora visualização dos alimentos e reduz desperdício. | D6: Famílias e pessoas que preparam refeições | E6: 21.5 | F6: 9.5 | G6: 69.9 | H6: 9.5 | I6: 9 | J6: =IF(G6=0,0,(G6-E6-F6-H6-I6)/G6) | K6: Médio | L6: DropNacional | M6: Transformação visual da geladeira | N6: Checar dimensão, material e embalagem.
A7: Cozinha prática | B7: Cortador/descascador prático | C7: Economiza tempo no preparo de alimentos. | D7: Quem cozinha em casa | E7: 16.8 | F7: 9.2 | G7: 54.9 | H7: 8.5 | I7: 8 | J7: =IF(G7=0,0,(G7-E7-F7-H7-I7)/G7) | K7: Baixo | L7: Dropi | M7: Uso real com alimento comum | N7: Evitar prometer desempenho exagerado.
A8: Automotivo leve | B8: Suporte veicular para celular | C8: Facilita visualização do celular com mais organização. | D8: Motoristas e motoristas de aplicativo | E8: 17.4 | F8: 10 | G8: 59.9 | H8: 8.5 | I8: 8.5 | J8: =IF(G8=0,0,(G8-E8-F8-H8-I8)/G8) | K8: Baixo | L8: AliExpress + DSers | M8: Instalação no painel com tomada curta | N8: Checar compatibilidade e fixação.
A9: Automotivo leve | B9: Lixeira dobrável para carro | C9: Mantém o carro limpo e ocupa pouco espaço. | D9: Motoristas, famílias e viagens | E9: 19.2 | F9: 9.8 | G9: 64.9 | H9: 8.5 | I9: 8.5 | J9: =IF(G9=0,0,(G9-E9-F9-H9-I9)/G9) | K9: Baixo | L9: Dropi | M9: Antes/depois do interior do carro | N9: Boa demonstração para Reels.
A10: Automotivo leve | B10: Organizador de banco de carro | C10: Evita objetos soltos no banco traseiro. | D10: Famílias, motoristas e pessoas que viajam | E10: 22.3 | F10: 10.5 | G10: 69.9 | H10: 9 | I10: 9 | J10: =IF(G10=0,0,(G10-E10-F10-H10-I10)/G10) | K10: Médio | L10: AliExpress + DSers | M10: Demonstração em carro real | N10: Validar costura e tamanho.
A11: Pet utilitário | B11: Tapete higiênico lavável para pet | C11: Ajuda na rotina de higiene e reduz descartáveis. | D11: Tutores de cães em apartamento | E11: 29.5 | F11: 12 | G11: 89.9 | H11: 10 | I11: 10 | J11: =IF(G11=0,0,(G11-E11-F11-H11-I11)/G11) | K11: Médio | L11: DropNacional | M11: Rotina de limpeza sem promessa veterinária | N11: Amostra é essencial para validar absorção.
A12: Pet utilitário | B12: Bebedouro portátil para pet | C12: Facilita hidratação em passeios e viagens. | D12: Tutores que passeiam com pets | E12: 26 | F12: 11.5 | G12: 79.9 | H12: 9.5 | I12: 9.5 | J12: =IF(G12=0,0,(G12-E12-F12-H12-I12)/G12) | K12: Médio | L12: Dropi | M12: Uso real em passeio | N12: Validar vedação e material.
A13: Cozinha prática | B13: Porta-temperos organizador | C13: Organiza temperos e libera espaço. | D13: Famílias e cozinhas pequenas | E13: 20 | F13: 9.2 | G13: 59.9 | H13: 8.5 | I13: 8 | J13: =IF(G13=0,0,(G13-E13-F13-H13-I13)/G13) | K13: Baixo | L13: DropNacional | M13: Antes/depois do armário | N13: Boa aceitação em conteúdo de organização.
... A23: Cozinha prática | B23: Tampa de silicone multiuso | C23: Ajuda a conservar alimentos e reduzir sujeira. | D23: Famílias e pessoas que cozinham | E23: 13.8 | F23: 8.9 | G23: 44.9 | H23: 7.5 | I23: 6.5 | J23: =IF(G23=0,0,(G23-E23-F23-H23-I23)/G23) | K23: Baixo | L23: DropNacional | M23: Teste real com potes de tamanhos diferentes | N23: Validar material e embalagem individual.

Sheet 05 Fornecedores
A1: Fornecedor/Plataforma | B1: Tipo | C1: Melhor uso | D1: Vantagens | E1: Desvantagens | F1: Prazo estimado | G1: Integrações | H1: Custo aproximado | I1: Nível de confiança | J1: Indicado para iniciante | K1: Cuidados antes de usar | L1: Link oficial ou campo para validação
A2: Dropi | B2: Plataforma brasileira | C2: Centralizar operação de dropshipping no Brasil | D2: Integrações e operação mais simples para iniciantes | E2: Plano, catálogo e fornecedores disponíveis mudam com o tempo | F2: 3 a 10 dias | G2: Nuvemshop, Shopify, WooCommerce, Yampi, AliExpress, CJdropshipping e SourcinBox | H2: Variável | I2: Alta | J2: Sim | K2: Validar plano atual, catálogo, logística, prazo e reputação | L2: validar no site oficial
A3: DropNacional | B3: Rede de fornecedores nacionais | C3: Reduzir prazo e evitar longa importação | D3: Prazo menor e mais controle sobre entrega | E3: Catálogo pode ser menor e margem pode apertar | F3: 1 a 7 dias | G3: Nuvemshop, Shopify, WooCommerce e operação manual | H3: Variável | I3: Alta | J3: Sim | K3: Verificar catálogo, margem, reputação e política de troca | L3: validar no site oficial
A4: AliExpress + DSers | B4: Marketplace internacional + app de pedidos | C4: Testar produtos com grande variedade | D4: Muito conhecido, catálogo enorme e fácil de encontrar tendências | E4: Prazo pode ser alto, qualidade varia e exige análise rigorosa | F4: 10 a 25 dias | G4: Shopify, WooCommerce e Nuvemshop conforme integração disponível | H4: Gratuito/variável | I4: Média | J4: Sim com cautela | K4: Analisar avaliações, pedidos, fotos reais, prazo para o Brasil e rastreio | L4: validar no site oficial
A5: CJdropshipping | B5: Sourcing e fulfillment internacional | C5: Escalar produtos já validados | D5: Sourcing, fulfillment e variedade de produtos | E5: Prazo, frete e disponibilidade de armazém variam | F5: 7 a 20 dias | G5: Shopify, WooCommerce e outras integrações | H5: Variável | I5: Média | J5: Parcial | K5: Validar prazo, frete, armazéns disponíveis e custo final para o Brasil | L5: validar no site oficial
A6: SourcinBox | B6: Sourcing/fulfillment | C6: Encontrar fornecedores e melhorar logística | D6: Pode ajudar no sourcing e na operação quando há volume | E6: Menos útil antes da validação do produto | F6: 7 a 20 dias | G6: Shopify, WooCommerce e operação conforme disponibilidade | H6: Variável | I6: Média | J6: Não no primeiro teste | K6: Usar após validar produto, margem e demanda | L6: validar no site oficial
A7: Zendrop | B7: Plataforma internacional | C7: Alternativa estruturada para dropshipping | D7: Boa estrutura operacional e automações | E7: Pode ter custo em dólar e logística menos vantajosa para Brasil | F7: 7 a 20 dias | G7: Shopify, WooCommerce e integrações disponíveis | H7: Variável/dólar | I7: Média | J7: Parcial | K7: Comparar custo em reais, prazo e suporte ao Brasil | L7: validar no site oficial
A8: Spocket | B8: Fornecedores EUA/Europa | C8: Alternativa internacional | D8: Catálogo curado e bons fornecedores em alguns mercados | E8: Pode não ser ideal para Brasil no começo | F8: 7 a 25 dias | G8: Shopify, WooCommerce e integrações disponíveis | H8: Variável/dólar | I8: Média | J8: Não no começo | K8: Verificar prazo, frete e custo final para clientes no Brasil | L8: validar no site oficial
A9: Fornecedor nacional direto | B9: Fabricante/distribuidor | C9: Ter prazo menor e mais controle | D9: Negociação direta, melhor prazo e possível margem maior | E9: Exige prospecção, negociação e controle manual | F9: 1 a 7 dias | G9: Manual, WhatsApp, planilha ou ERP simples | H9: Variável | I9: Alta se validado | J9: Sim | K9: Confirmar CNPJ, reputação, nota fiscal, prazo, política de troca e estoque | L9: validar no site oficial
A10: Mercado Livre atacado | B10: Marketplace B2B/atacado | C10: Testar produtos com envio mais rápido | D10: Acesso fácil a vendedores nacionais e entrega previsível | E10: Margem e reputação variam muito | F10: 2 a 7 dias | G10: Manual | H10: Variável | I10: Média | J10: Parcial | K10: Verificar reputação, nota fiscal, estoque, margem e autorização de revenda | L10: validar no site oficial
A11: Shopee fornecedores/atacado | B11: Marketplace com vendedores e atacadistas | C11: Buscar itens de baixo investimento | D11: Catálogo amplo e preços competitivos | E11: Qualidade, prazo e reputação precisam ser verificados com rigor | F11: 5 a 15 dias | G11: Manual | H11: Variável | I11: Média | J11: Parcial | K11: Comprar amostra, verificar avaliações, reputação e documentação | L11: validar no site oficial

Sheet 06 Custos_Iniciais
A1: Categoria | B1: Item | C1: Econômico | D1: Intermediário | E1: Profissional | F1: Observações
A2: Loja | B2: Plataforma de loja | C2: 29 | D2: 79 | E2: 299 | F2: Plano mensal inicial ou teste pago.
A3: Domínio | B3: Domínio | C3: 40 | D3: 70 | E3: 120 | F3: Nome próprio aumenta confiança.
A4: Design | B4: Tema | C4: 0 | D4: 150 | E4: 500 | F4: Tema gratuito, pago ou customização.
A5: Apps | B5: Apps e integrações | C5: 0 | D5: 120 | E5: 600 | F5: Pagamento, avaliações, logística e recuperação de carrinho.
A6: Integração | B6: Dropi ou ferramenta de integração | C6: 0 | D6: 99 | E6: 299 | F6: Usar se realmente reduzir trabalho operacional.
A7: Marketing | B7: Anúncios | C7: 150 | D7: 800 | E7: 3000 | F7: Testes controlados; não escalar sem margem.
A8: Validação | B8: Compra de amostras | C8: 80 | D8: 250 | E8: 600 | F8: Obrigatório para produto principal.
A9: Conteúdo | B9: Edição de vídeo | C9: 0 | D9: 250 | E9: 1000 | F9: CapCut próprio, freelancer ou pacote de criativos.
A10: Conteúdo | B10: Criativos | C10: 50 | D10: 200 | E10: 600 | F10: Imagens, vídeos, variações e testes.
A11: Operação | B11: Reserva para reembolso | C11: 100 | D11: 300 | E11: 1000 | F11: Reserva evita quebrar por troca ou atraso.
A12: Financeiro | B12: Taxas de pagamento | C12: 20 | D12: 80 | E12: 200 | F12: Processamento, antifraude e tarifas.
A13: Legal | B13: Contabilidade | C13: 0 | D13: 120 | E13: 500 | F13: Validar necessidade com contador.
... A16: Capital de giro | B16: Capital de giro | C16: 300 | D16: 1200 | E16: 2000 | F16: Cobertura para pedidos, prazo e contingência.
B17: Total estimado | C17: =SUM(C2:C16) | D17: =SUM(D2:D16) | E17: =SUM(E2:E16) | F17: Soma das categorias

Sheet 07 Precificacao
A1: Calculadora de preço, margem e CPA
A2: Campos azuis são editáveis. Campos amarelos são fórmulas protegidas contra alteração acidental. Ajuste as taxas conforme sua plataforma e valide imposto com contador.
A4: Campo editável | B4: Valor | C4: Observação
A5: Custo do produto | B5: 29.9 | C5: Valor pago ao fornecedor por unidade
A6: Frete | B6: 12.5 | C6: Custo de envio médio por unidade
A7: Taxa da plataforma | B7: 0.05 | C7: Percentual sobre venda
A8: Taxa do pagamento | B8: 0.032 | C8: Percentual do gateway/antifraude
A9: Imposto estimado | B9: 0.06 | C9: Estimativa; validar com contador
A10: CPA/anúncio | B10: 8 | C10: Custo máximo por compra
A11: Reserva para reembolso | B11: 3.5 | C11: Valor reservado por pedido
A12: Margem desejada | B12: 0.35 | C12: Margem líquida alvo
A14: Campo calculado | B14: Valor | C14: Leitura
A15: Custo fixo por pedido | B15: =B5+B6+B10+B11 | C15: Produto + frete + CPA + reserva de reembolso
A16: Percentual consumido por taxas + margem | B16: =B7+B8+B9+B12 | C16: Se chegar perto de 100%, a operação é inviável
A17: Preço mínimo | B17: =IF(B15>=1,"Rever taxas/margem",B14/(1-B15)) | C17: Menor preço para atingir a margem desejada
A18: Preço sugerido | B18: =IF(ISNUMBER(B16),ROUNDUP(B16*1.05,0)-0.1,"Rever entradas") | C18: Preço com pequena folga comercial
A19: Receita líquida após taxas | B19: =IF(ISNUMBER(B17),B17*(1-B7-B8-B9),"") | C19: Venda menos taxas percentuais
A20: Custo total operacional | B20: =B14 | C20: Custo fixo do pedido
A21: Lucro líquido por pedido | B21: =IF(ISNUMBER(B17),B18-B19,"") | C21: Resultado depois de produto, frete, CPA, reserva e taxas
A22: Margem percentual | B22: =IF(ISNUMBER(B17),B20/B17,"") | C22: Lucro líquido dividido pelo preço de venda
A23: ROI de anúncio | B23: =IF(B10>0,B20/B10,"") | C23: Lucro líquido dividido pelo CPA
A25: Regra prática | B25: Se o preço sugerido ficar fora do valor percebido pelo cliente ou a margem ficar abaixo de 20%, revise produto, fornecedor, frete, CPA ou oferta antes de anunciar.

Sheet 08 Loja
A1: Item | B1: Por que é importante | C1: Como fazer bem | D1: Erro comum | E1: Status
A2: Nome | B2: Marca e identificação | C2: Escolher nome claro, memorável e fácil de escrever | D2: Nome genérico ou difícil | E2: Pendente
A3: Logo | B3: Cria confiança | C3: Usar logo simples, legível e coerente com a categoria | D3: Logo poluído | E3: Pendente
A4: Paleta | B4: Ajuda a transmitir profissionalismo | C4: Usar 2 a 3 cores com contraste suficiente | D4: Cores fortes demais | E4: Pendente
A5: Domínio | B5: Facilita lembrança | C5: Escolher nome curto e sem caracteres estranhos | D5: Domínio longo | E5: Pendente
A6: Página inicial | B6: Define primeira impressão | C6: Mostrar categoria, benefício, produto e prova social honesta | D6: Página confusa | E6: Pendente
A7: Página de produto | B7: Aumenta conversão | C7: Foto, vídeo, descrição, preço, prazo e CTA visível | D7: Texto genérico | E7: Pendente
A8: Fotos | B8: Mostram o produto com realismo | C8: Usar imagens reais ou autorizadas e boa iluminação | D8: Foto copiada sem autorização | E8: Pendente
A9: Vídeos | B9: Aumentam confiança | C9: Mostrar uso real, antes/depois e escala do produto | D9: Vídeo sem contexto | E9: Pendente
A10: Descrição | B10: Explica benefício e uso | C10: Escrever problema, solução, conteúdo da embalagem e cuidados | D10: Promessa exagerada | E10: Pendente
A11: Prova social | B11: Reduz dúvida | C11: Usar avaliações reais e políticas transparentes | D11: Depoimento inventado | E11: Pendente
A12: Frete | B12: Evita frustração | C12: Informar prazo realista e rastreio | D12: Prazo curto sem base | E12: Pendente
... A19: Teste de compra | B19: Valida processo inteiro | C19: Fazer pedido real e revisar e-mails, pagamento e rastreio | D19: Não testar | E19: Pendente

Sheet 09 Anuncios_Pagos
A1: Dia/Semana | B1: Plataforma | C1: Objetivo | D1: Campanha | E1: Orçamento diário | F1: Criativos | G1: Métrica principal | H1: Regra para pausar | I1: Regra para escalar | J1: Observações
A2: Dias 1 a 7 | B2: Meta Ads / TikTok Ads | C2: Pesquisa e criativos | D2: Teste de audiência inicial | E2: R$ 10 a R$ 20 | F2: 3 a 5 criativos por produto | G2: CTR, retenção e CPC | H2: CTR baixo ou CPC alto sem sinal de compra | I2: Não escalar nesta fase | J2: Validar promessa, ângulo e página antes de gastar mais.
A3: Dias 8 a 14 | B3: Meta Ads / TikTok Ads | C3: Testes pequenos | D3: Campanhas de 1 produto | E3: R$ 20 a R$ 40 | F3: 2 a 3 criativos vencedores | G3: CPA, checkout e conversão | H3: Sem venda após gasto relevante ao CPA máximo | I3: Escalar só se houver margem positiva | J3: Separar orçamento por produto e pausar rápido o que não responde.
A4: Dias 15 a 21 | B4: Meta Ads / TikTok Ads | C4: Otimização | D4: Ajuste de criativos, público e oferta | E4: R$ 30 a R$ 60 | F4: Variações do melhor criativo | G4: ROAS e lucro líquido | H4: CPA acima do limite por 2 dias | I4: Aumentar 15% a 25% com dados | J4: Revisar frete, preço, prova social e checkout.
A5: Dias 22 a 30 | B5: Meta Ads / TikTok Ads | C5: Escala controlada | D5: Campanha com melhor performance | E5: R$ 40 a R$ 80 | F5: Criativo principal + variações | G5: Lucro líquido e reclamações | H5: Queda de margem, atraso ou reclamação | I5: Escalar gradualmente mantendo reserva | J5: Não aumentar orçamento se fornecedor estiver instável.

Sheet 10 Trafego_Organico
A1: Plataforma | B1: Frequência | C1: Tipo de vídeo | D1: Roteiro curto | E1: Objetivo | F1: Produto ideal | G1: CTA
A2: TikTok | B2: 5 a 7 vídeos/semana | C2: Antes e depois | D2: Mostre o problema, aplique o produto e finalize com o resultado | E2: Gerar alcance e salvar criativos vencedores | F2: Organizador de cabos | G2: Comente 'quero' ou acesse a loja
A3: Instagram Reels | B3: 4 a 5 vídeos/semana | C3: Demonstração rápida | D3: Mostre uso real nos primeiros 3 segundos | E3: Construir confiança e remarketing | F3: Suporte adesivo para tomada | G3: Salve para testar em casa
A4: YouTube Shorts | B4: 3 a 4 vídeos/semana | C4: Teste real | D4: Compare rotina antes/depois com legenda objetiva | E4: Gerar busca e prova de uso | F4: Escova removedora de pelos | G4: Veja mais detalhes na loja
A5: Pinterest | B5: 2 a 3 pins/semana | C5: Organização visual | D5: Foto ou vídeo curto com resultado organizado | E5: Tráfego de cauda longa | F5: Organizador de geladeira | G5: Clique para ver a lista completa
A6: TikTok | B6: 3 vídeos/semana | C6: 3 coisas que resolvem... | D6: Liste três problemas e mostre uma solução prática | E6: Testar ângulos de comunicação | F6: Escova multifuncional | G6: Siga para mais soluções simples
A7: Instagram Reels | B7: 2 vídeos/semana | C7: Cozinha prática | D7: Mostre preparo mais rápido ou espaço organizado | E7: Aumentar percepção de valor | F7: Escorredor dobrável | G7: Veja o produto em uso
A8: YouTube Shorts | B8: 2 vídeos/semana | C8: Carro organizado | D8: Mostre interior bagunçado, aplicação e resultado | E8: Validar nicho automotivo leve | F8: Lixeira dobrável para carro | G8: Confira medidas e detalhes
A9: TikTok | B9: 2 vídeos/semana | C9: Produto sendo usado por pet | D9: Mostre o pet, o problema e o uso sem promessa veterinária | E9: Validar apelo emocional | F9: Bebedouro portátil | G9: Comente se seu pet usaria

Sheet 11 Cronograma_30_Dias
A1: Dia | B1: Objetivo | C1: Tarefas | D1: Entregável do dia | E1: Ferramentas | F1: Tempo estimado | G1: Status
A2: 1 | B2: Definir nicho e posicionamento | C2: Pesquisar dores, concorrentes e demanda | D2: Lista de 10 ideias de produto | E2: Google Trends, TikTok, Instagram | F2: 2h | G2: Pendente
A3: 2 | B3: Selecionar produtos | C3: Filtrar produtos com utilidade clara e baixo risco | D3: 5 produtos priorizados | E3: Planilha, marketplaces | F3: 2h | G3: Pendente
A4: 3 | B4: Escolher fornecedores | C4: Comparar Dropi, DSers, DropNacional e opções diretas | D4: Fornecedor preferido e alternativa | E4: Dropi, DSers, DropNacional | F4: 2h | G4: Pendente
A5: 4 | B5: Validar margem | C5: Calcular custo, frete, taxas, CPA máximo e reserva | D5: Tabela de margem por produto | E5: Aba Precificacao | F5: 2h | G5: Pendente
A6: 5 | B6: Comprar amostra | C6: Solicitar amostra do produto principal | D6: Pedido de amostra registrado | E6: Fornecedor | F6: 1h | G6: Pendente
A7: 6 | B7: Definir marca | C7: Nome, logo, paleta e tom de voz | D7: Branding básico | E7: Canva | F7: 2h | G7: Pendente
A8: 7 | B8: Montar estrutura da loja | C8: Criar conta, tema, menus e páginas principais | D8: Loja base pronta | E8: Nuvemshop/Shopify/Yampi | F8: 3h | G8: Pendente
A9: 8 | B9: Configurar pagamentos | C9: Ativar gateway, antifraude e dados de recebimento | D9: Checkout funcional | E9: Gateway de pagamento | F9: 1h | G9: Pendente
A10: 9 | B10: Criar políticas | C10: Troca, privacidade, termos e prazo de entrega | D10: Políticas publicadas | E10: Editor da loja | F10: 2h | G10: Pendente
A11: 10 | B11: Criar página de produto | C11: Texto, fotos, vídeo, preço, prazo e FAQ | D11: Página pronta | E11: Canva, CapCut, loja | F11: 3h | G11: Pendente
A12: 11 | B12: Criar criativos | C12: Produzir vídeos curtos e variações de gancho | D12: 3 a 5 criativos | E12: CapCut | F12: 3h | G12: Pendente
A13: 12 | B13: Configurar pixel | C13: Instalar eventos e testar tracking | D13: Pixel funcionando | E13: Meta Ads, TikTok Ads | F13: 1h | G13: Pendente
... A31: 30 | B31: Revisão final | C31: Decidir continuar, pausar ou trocar produto | D31: Decisão de continuidade | E31: Planilha e métricas | F31: 2h | G31: Pendente

Sheet 12 Riscos
A1: Problema | B1: Causa | C1: Consequência | D1: Como prevenir | E1: Como resolver | F1: Gravidade | G1: Probabilidade
A2: Atraso na entrega | B2: Fornecedor lento ou logística instável | C2: Cliente insatisfeito e pedido de reembolso | D2: Validar prazo realista e ter rastreio | E2: Comunicar rápido, oferecer solução e revisar fornecedor | F2: Alta | G2: Média
A3: Fornecedor ruim | B3: Baixa qualidade ou falta de estoque | C3: Reembolso, reclamação e perda de margem | D3: Comprar amostra e checar reputação | E3: Trocar fornecedor e pausar anúncio | F3: Alta | G3: Média
A4: Produto de baixa qualidade | B4: Material frágil ou acabamento ruim | C4: Devolução e reclamação pública | D4: Validar amostra e avaliações reais | E4: Substituir produto e atender cliente | F4: Alta | G4: Média
A5: Chargeback | B5: Pedido contestado ou atendimento ruim | C5: Perda financeira e risco no gateway | D5: Políticas claras, comprovantes e rastreio | E5: Responder com evidências e melhorar comunicação | F5: Alta | G5: Média
A6: Reembolso | B6: Cliente insatisfeito, atraso ou defeito | C6: Erosão de margem | D6: Manter reserva e prazo transparente | E6: Aplicar política de forma justa | F6: Média | G6: Alta
A7: Cliente insatisfeito | B7: Falta de informação ou expectativa errada | C7: Reclamação pública e queda de confiança | D7: Texto claro e atendimento em até 24h | E7: Responder com empatia e solução objetiva | F7: Alta | G7: Média
A8: Conta de anúncio bloqueada | B8: Promessa exagerada ou política violada | C8: Parada de tráfego | D8: Evitar claims sensíveis e revisar regras | E8: Reformular criativos e recorrer se aplicável | F8: Alta | G8: Baixa
A9: Produto saturado | B9: Concorrência alta e criativos iguais | C9: CPC alto e baixa conversão | D9: Testar ângulos e produtos relacionados | E9: Trocar oferta ou produto | F9: Média | G9: Média
A10: Margem baixa | B10: Frete, taxas e CPA acima do planejado | C10: Negócio sem lucro | D10: Calcular margem antes de anunciar | E10: Ajustar preço, oferta, fornecedor ou pausar | F10: Alta | G10: Alta
A11: Reclamação pública | B11: Atendimento lento ou promessa não cumprida | C11: Dano reputacional | D11: Responder rápido e documentar tudo | E11: Resolver com transparência e aprendizado | F11: Alta | G11: Média
A12: Problemas com importação | B12: Mercadoria internacional, taxa ou retenção | C12: Atraso, custo extra ou cancelamento | D12: Preferir fornecedor nacional no começo | E12: Usar alternativa nacional e informar cliente | F12: Alta | G12: Média
... A16: Falta de capital de giro | B16: Crescimento sem reserva | C16: Pedidos atrasados e pausa forçada | D16: Separar caixa e reserva de reembolso | E16: Reduzir escala e reorganizar fluxo de caixa | F16: Alta | G16: Média

Sheet 13 Legal_Brasil
A1: Tema | B1: Explicação simples | C1: O que fazer | D1: Risco se ignorar | E1: Fonte ou validação
A2: CDC | B2: As regras do Código de Defesa do Consumidor se aplicam ao e-commerce. | C2: Ter políticas claras, atendimento e registros. | D2: Reclamações, sanções e perda de confiança. | E2: Validar com contador, advogado ou fonte oficial.
A3: Direito de arrependimento | B3: Compras online têm regra de desistência em prazo legal. | C3: Informar procedimento de devolução e contato. | D3: Conflito com cliente e órgãos de defesa. | E3: Validar com fonte oficial.
A4: Política de troca e devolução | B4: Cliente precisa entender prazos, condições e fluxo. | C4: Publicar política simples antes de vender. | D4: Reembolso improvisado e disputa. | E4: Validar com fonte oficial.
A5: Transparência no prazo de entrega | B5: Prazo precisa ser claro e realista. | C5: Informar prazo conservador e rastreio. | D5: Insatisfação e reclamação. | E5: Validar com fonte oficial.
A6: CNPJ/MEI | B6: A formalização depende da atividade, faturamento e estrutura. | C6: Consultar contador antes de escalar. | D6: Problemas fiscais e limite de operação. | E6: Validar com contador.
A7: Nota fiscal | B7: A emissão depende do modelo fiscal aplicável. | C7: Entender obrigação antes de vender volume. | D7: Risco fiscal e dificuldade com fornecedores. | E7: Validar com contador.
A8: Limite anual do MEI | B8: MEI tem limite de faturamento e atividades permitidas. | C8: Acompanhar receita mensal e projeção. | D8: Desenquadramento e imposto retroativo. | E8: Validar com contador ou fonte oficial.
A9: Importação | B9: Importar pode ter imposto, documentação e retenção. | C9: Checar regra, prazo, rastreio e custo final. | D9: Atraso, custo extra e insatisfação. | E9: Validar com Receita Federal ou fonte oficial.
A10: Remessa Conforme | B10: Compras internacionais podem exigir procedimentos específicos. | C10: Usar fornecedores com documentação e rastreio. | D10: Problemas na entrega e custo inesperado. | E10: Validar com fonte oficial.
A11: Produtos proibidos | B11: Algumas categorias exigem autorização ou são restritas. | C11: Checar produto antes de cadastrar. | D11: Bloqueio, multa e risco legal. | E11: Validar com fonte oficial.
A12: Promessas enganosas | B12: Benefícios exagerados geram risco legal e bloqueios. | C12: Usar comunicação honesta e demonstrável. | D12: Reclamações e bloqueio de anúncio. | E12: Validar políticas de anúncio e fonte oficial.
... A14: LGPD | B14: Dados de clientes precisam de finalidade, cuidado e transparência. | C14: Ter aviso de privacidade e proteger acessos. | D14: Sanções e perda de confiança. | E14: Validar com fonte oficial ou jurídico.
A16: Aviso | B16: Esta aba é orientação operacional básica, não aconselhamento jurídico definitivo.

Sheet 14 Ferramentas
A1: Categoria | B1: Ferramenta | C1: Função | D1: Preço aproximado | E1: Tem plano grátis? | F1: Alternativa gratuita | G1: Vale para iniciante? | H1: Observações
A2: Loja | B2: Nuvemshop | C2: Loja simples e rápida para Brasil | D2: R$ 29 a R$ 119/mês | E2: Sim | F2: Teste grátis ou plano inicial | G2: Sim | H2: Boa para começar com operação nacional.
A3: Loja | B3: Shopify | C3: Loja completa e ecossistema amplo | D3: R$ 39 a R$ 399/mês | E3: Trial | F3: Nuvemshop | G3: Sim | H3: Boa para crescer, mas validar custo em reais.
A4: Loja | B4: WooCommerce | C4: Loja com WordPress | D4: Variável | E4: Sim | F4: Nuvemshop | G4: Parcial | H4: Mais controle, exige manutenção.
A5: Loja | B5: Yampi | C5: Checkout e estrutura de loja | D5: Variável | E5: Sim | F5: Nuvemshop | G5: Sim | H5: Muito usada no mercado brasileiro.
A6: Domínio | B6: Registro.br ou registrador equivalente | C6: Comprar domínio próprio | D6: R$ 40 a R$ 80/ano | E6: Não | F6: Subdomínio temporário | G6: Sim | H6: Domínio próprio melhora confiança.
A7: Design | B7: Canva | C7: Criar posts, banners e identidade | D7: Grátis / pago | E7: Sim | F7: Photopea | G7: Sim | H7: Excelente para MVP.
A8: Vídeo | B8: CapCut | C8: Editar vídeos curtos | D8: Grátis / pago | E8: Sim | F8: VN | G8: Sim | H8: Útil para TikTok/Reels.
A9: Anúncios | B9: Meta Ads | C9: Campanhas no Facebook e Instagram | D9: Orçamento variável | E9: Não | F9: Conteúdo orgânico | G9: Sim | H9: Começar com orçamento pequeno.
A10: Anúncios | B10: TikTok Ads | C10: Campanhas na plataforma TikTok | D10: Orçamento variável | E10: Não | F10: Conteúdo orgânico | G10: Sim | H10: Bom para vídeos curtos.
A11: Atendimento | B11: WhatsApp Business | C11: Atendimento, catálogo e respostas rápidas | D11: Grátis | E11: Sim | F11: E-mail | G11: Sim | H11: Canal essencial no Brasil.
A12: Rastreio | B12: Melhor Envio | C12: Frete, rastreio e logística quando aplicável | D12: Grátis / variável | E12: Sim | F12: Rastreio manual | G12: Sim | H12: Útil para fornecedores nacionais.
... A21: Automação | B21: Planilha + rotinas simples | C21: Controle inicial de pedidos e margem | D21: Grátis | E21: Sim | F21: Google Sheets | G21: Sim | H21: Automatizar só depois de validar.

Sheet 15 Financeiro_3_Meses
A1: Projeção financeira estimada para 3 meses
A2: Use como simulação. O resultado real depende de produto, criativo, fornecedor, tráfego, atendimento e execução.
A4: Mês | B4: Cenário | C4: Visitas | D4: Taxa de conversão | E4: Pedidos | F4: Ticket médio | G4: Faturamento | H4: Custo dos produtos | I4: Frete | J4: Taxas | K4: Anúncios | L4: Ferramentas | M4: Reembolsos | N4: Lucro líquido | O4: Margem líquida
A5: Mês 1 | B5: Ruim | C5: 1200 | D5: 0.006 | E5: =ROUND(C5*D5,0) | F5: 59 | G5: =E5*F5 | H5: =G5*0.42 | I5: =G5*0.10 | J5: =G5*0.075 | K5: =C5*0.32 | L5: 80 | M5: =G5*0.04 | N5: =G5-H5-I5-J5-K5-L5-M5 | O5: =IF(G5=0,0,N5/G5)
A6: Mês 2 | B6: Ruim | C6: 1500 | D6: 0.008 | E6: =ROUND(C6*D6,0) | F6: 62 | G6: =E6*F6 | H6: =G6*0.42 | I6: =G6*0.10 | J6: =G6*0.075 | K6: =C6*0.32 | L6: 80 | M6: =G6*0.04 | N6: =G6-H6-I6-J6-K6-L6-M6 | O6: =IF(G6=0,0,N6/G6)
A7: Mês 3 | B7: Ruim | C7: 1800 | D7: 0.01 | E7: =ROUND(C7*D7,0) | F7: 65 | G7: =E7*F7 | H7: =G7*0.42 | I7: =G7*0.10 | J7: =G7*0.075 | K7: =C7*0.32 | L7: 80 | M7: =G7*0.04 | N7: =G7-H7-I7-J7-K7-L7-M7 | O7: =IF(G7=0,0,N7/G7)
A8: Mês 1 | B8: Médio | C8: 3000 | D8: 0.014 | E8: =ROUND(C8*D8,0) | F8: 75 | G8: =E8*F8 | H8: =G8*0.42 | I8: =G8*0.10 | J8: =G8*0.075 | K8: =C8*0.28 | L8: 120 | M8: =G8*0.04 | N8: =G8-H8-I8-J8-K8-L8-M8 | O8: =IF(G8=0,0,N8/G8)
A9: Mês 2 | B9: Médio | C9: 3800 | D9: 0.017 | E9: =ROUND(C9*D9,0) | F9: 79 | G9: =E9*F9 | H9: =G9*0.42 | I9: =G9*0.10 | J9: =G9*0.075 | K9: =C9*0.28 | L9: 120 | M9: =G9*0.04 | N9: =G9-H9-I9-J9-K9-L9-M9 | O9: =IF(G9=0,0,N9/G9)
A10: Mês 3 | B10: Médio | C10: 4600 | D10: 0.02 | E10: =ROUND(C10*D10,0) | F10: 84 | G10: =E10*F10 | H10: =G10*0.42 | I10: =G10*0.10 | J10: =G10*0.075 | K10: =C10*0.28 | L10: 120 | M10: =G10*0.04 | N10: =G10-H10-I10-J10-K10-L10-M10 | O10: =IF(G10=0,0,N10/G10)
A11: Mês 1 | B11: Bom | C11: 5000 | D11: 0.022 | E11: =ROUND(C11*D11,0) | F11: 85 | G11: =E11*F11 | H11: =G11*0.42 | I11: =G11*0.10 | J11: =G11*0.075 | K11: =C11*0.22 | L11: 180 | M11: =G11*0.04 | N11: =G11-H11-I11-J11-K11-L11-M11 | O11: =IF(G11=0,0,N11/G11)
A12: Mês 2 | B12: Bom | C12: 6500 | D12: 0.026 | E12: =ROUND(C12*D12,0) | F12: 90 | G12: =E12*F12 | H12: =G12*0.42 | I12: =G12*0.10 | J12: =G12*0.075 | K12: =C12*0.22 | L12: 180 | M12: =G12*0.04 | N12: =G12-H12-I12-J12-K12-L12-M12 | O12: =IF(G12=0,0,N12/G12)
A13: Mês 3 | B13: Bom | C13: 8000 | D13: 0.03 | E13: =ROUND(C13*D13,0) | F13: 95 | G13: =E13*F13 | H13: =G13*0.42 | I13: =G13*0.10 | J13: =G13*0.075 | K13: =C13*0.22 | L13: 180 | M13: =G13*0.04 | N13: =G13-H13-I13-J13-K13-L13-M13 | O13: =IF(G13=0,0,N13/G13)
A16: Cenário | B16: Lucro líquido no mês 3 | C16: Margem líquida no mês 3 | D16: Faturamento no mês 3
A17: Ruim | B17: =N7 | C17: =O7 | D17: =G7
A18: Médio | B18: =N10 | C18: =O10 | D18: =G10
A19: Bom | B19: =N13 | C19: =O13 | D19: =G13

Sheet 16 Checklist_Final
A1: Categoria | B1: Item | C1: Obrigatório? | D1: Status | E1: Observação
A2: Nicho | B2: Nicho escolhido | C2: Sim | D2: Pendente | E2: Validar demanda, margem e risco.
A3: Produto | B3: Produto validado | C3: Sim | D3: Pendente | E3: Checar utilidade, amostra e defeitos.
A4: Fornecedor | B4: Fornecedor analisado | C4: Sim | D4: Pendente | E4: Confirmar prazo, estoque, rastreio e qualidade.
A5: Validação | B5: Amostra comprada ou validada | C5: Sim | D5: Pendente | E5: Testar antes do anúncio pago.
A6: Finanças | B6: Margem calculada | C6: Sim | D6: Pendente | E6: Usar a aba de precificação.
A7: Loja | B7: Loja revisada | C7: Sim | D7: Pendente | E7: Checar páginas, imagens, CTA e confiança.
A8: Checkout | B8: Checkout testado | C8: Sim | D8: Pendente | E8: Validar pagamento, e-mails e pedido.
A9: Políticas | B9: Políticas criadas | C9: Sim | D9: Pendente | E9: Troca, privacidade, termos e prazo.
A10: Prazo | B10: Prazo de entrega claro | C10: Sim | D10: Pendente | E10: Não prometer prazo curto sem base.
A11: Atendimento | B11: Suporte configurado | C11: Sim | D11: Pendente | E11: WhatsApp e e-mail com rotina diária.
A12: Criativos | B12: Criativos prontos | C12: Sim | D12: Pendente | E12: Vídeos curtos, claros e sem promessa exagerada.
... A19: Escala | B19: Plano de escala | C19: Sim | D19: Pendente | E19: Aumentar orçamento apenas com margem positiva.
